netbox_vitalqip/__init__.py
netbox_vitalqip/forms.py
netbox_vitalqip/navigation.py
netbox_vitalqip/qip_client.py
netbox_vitalqip/urls.py
netbox_vitalqip/views.py
netbox_vitalqip/templates/netbox_vitalqip/device_tab.html
netbox_vitalqip/templates/netbox_vitalqip/prefix_import.html
netbox_vitalqip/templates/netbox_vitalqip/prefix_import_preview.html
netbox_vitalqip/templates/netbox_vitalqip/settings.html
netbox_vitalqip-0.1.1.dist-info/licenses/LICENSE
netbox_vitalqip-0.1.1.dist-info/METADATA
netbox_vitalqip-0.1.1.dist-info/WHEEL
netbox_vitalqip-0.1.1.dist-info/top_level.txt
netbox_vitalqip-0.1.1.dist-info/RECORD
