Metadata-Version: 2.4
Name: netbox-vitalqip
Version: 0.1.1
Summary: NetBox plugin to display VitalQIP IPAM data and import IP addresses
Author-email: sieteunoseis <jeremy.worden@gmail.com>
License: Apache-2.0
Project-URL: Homepage, https://github.com/sieteunoseis/netbox-vitalqip
Project-URL: Repository, https://github.com/sieteunoseis/netbox-vitalqip
Project-URL: Issues, https://github.com/sieteunoseis/netbox-vitalqip/issues
Keywords: netbox,vitalqip,ipam,nokia,plugin
Classifier: Development Status :: 3 - Alpha
Classifier: Framework :: Django
Classifier: Intended Audience :: System Administrators
Classifier: License :: OSI Approved :: Apache Software License
Classifier: Programming Language :: Python :: 3
Classifier: Programming Language :: Python :: 3.10
Classifier: Programming Language :: Python :: 3.11
Classifier: Programming Language :: Python :: 3.12
Requires-Python: >=3.10
License-File: LICENSE
Requires-Dist: requests>=2.28.0
Provides-Extra: dev
Requires-Dist: black; extra == "dev"
Requires-Dist: flake8; extra == "dev"
Requires-Dist: isort; extra == "dev"
Requires-Dist: pytest; extra == "dev"
Dynamic: license-file
